{"biome":"storm-coast","built_at":"2026-05-19T23:55:51Z","schema":3,"tiers":{"common":[{"species":"blitzle","min":5,"max":15},{"species":"chinchou","min":5,"max":15},{"species":"dedenne","min":5,"max":15},{"species":"doduo","min":5,"max":15},{"species":"ducklett","min":5,"max":15},{"species":"emolga","min":5,"max":15},{"species":"fletchling","min":5,"max":15},{"species":"geodude","min":5,"max":15},{"species":"helioptile","min":5,"max":15},{"species":"hoothoot","min":5,"max":15},{"species":"hoppip","min":5,"max":15},{"species":"joltik","min":5,"max":15},{"species":"ledyba","min":5,"max":15},{"species":"magnemite","min":5,"max":15},{"species":"mareep","min":5,"max":15},{"species":"minun","min":5,"max":15},{"species":"morpeko","min":5,"max":15},{"species":"natu","min":5,"max":15},{"species":"noibat","min":5,"max":15},{"species":"pachirisu","min":5,"max":15},{"species":"pawmi","min":5,"max":15},{"species":"pichu","min":5,"max":15},{"species":"pidgey","min":5,"max":15},{"species":"pidove","min":5,"max":15},{"species":"pikachu","min":20,"max":30},{"species":"pikipek","min":5,"max":15},{"species":"plusle","min":5,"max":15},{"species":"rookidee","min":5,"max":15},{"species":"rufflet","min":5,"max":15},{"species":"shinx","min":5,"max":15},{"species":"spearow","min":5,"max":15},{"species":"squawkabilly","min":5,"max":15},{"species":"starly","min":5,"max":15},{"species":"swablu","min":5,"max":15},{"species":"tadbulb","min":5,"max":15},{"species":"taillow","min":5,"max":15},{"species":"togedemaru","min":5,"max":15},{"species":"tropius","min":5,"max":15},{"species":"tynamo","min":5,"max":15},{"species":"voltorb","min":5,"max":15},{"species":"vullaby","min":5,"max":15},{"species":"wattrel","min":5,"max":15},{"species":"wingull","min":5,"max":15},{"species":"woobat","min":5,"max":15},{"species":"yamper","min":5,"max":15},{"species":"zubat","min":5,"max":15}],"uncommon":[{"species":"charjabug","min":20,"max":30},{"species":"combee","min":5,"max":15},{"species":"corvisquire","min":18,"max":28},{"species":"crobat","min":35,"max":45},{"species":"drifloon","min":5,"max":15},{"species":"electrike","min":5,"max":15},{"species":"fearow","min":20,"max":30},{"species":"flaaffy","min":15,"max":25},{"species":"flamigo","min":5,"max":15},{"species":"fletchinder","min":17,"max":27},{"species":"galvantula","min":36,"max":46},{"species":"golbat","min":22,"max":32},{"species":"graveler","min":25,"max":35},{"species":"hawlucha","min":5,"max":15},{"species":"heliolisk","min":20,"max":30},{"species":"kilowattrel","min":25,"max":35},{"species":"lanturn","min":27,"max":37},{"species":"ledian","min":18,"max":28},{"species":"luxio","min":15,"max":25},{"species":"masquerain","min":22,"max":32},{"species":"ninjask","min":20,"max":30},{"species":"noctowl","min":20,"max":30},{"species":"pawmo","min":18,"max":28},{"species":"pidgeotto","min":18,"max":28},{"species":"pincurchin","min":5,"max":15},{"species":"raichu","min":35,"max":45},{"species":"skiploom","min":18,"max":28},{"species":"staravia","min":14,"max":24},{"species":"stunfisk","min":5,"max":15},{"species":"togetic","min":20,"max":30},{"species":"toxel","min":5,"max":15},{"species":"tranquill","min":21,"max":31},{"species":"trumbeak","min":14,"max":24},{"species":"xatu","min":25,"max":35},{"species":"yanma","min":5,"max":15},{"species":"zebstrika","min":27,"max":37}],"rare":[{"species":"aerodactyl","min":5,"max":15},{"species":"altaria","min":35,"max":45},{"species":"ampharos","min":30,"max":40},{"species":"archen","min":5,"max":15},{"species":"archeops","min":37,"max":47},{"species":"arctozolt","min":5,"max":15},{"species":"beautifly","min":10,"max":20},{"species":"bellibolt","min":20,"max":30},{"species":"boltund","min":25,"max":35},{"species":"bombirdier","min":5,"max":15},{"species":"braviary","min":54,"max":64},{"species":"butterfree","min":10,"max":20},{"species":"celesteela","min":5,"max":15},{"species":"charizard","min":36,"max":46},{"species":"chatot","min":5,"max":15},{"species":"clefable","min":35,"max":45},{"species":"corviknight","min":38,"max":48},{"species":"cramorant","min":5,"max":15},{"species":"dartrix","min":17,"max":27},{"species":"delibird","min":5,"max":15},{"species":"dodrio","min":31,"max":41},{"species":"dracozolt","min":5,"max":15},{"species":"dragonite","min":55,"max":65},{"species":"drifblim","min":28,"max":38},{"species":"eelektrik","min":39,"max":49},{"species":"eelektross","min":35,"max":45},{"species":"electabuzz","min":30,"max":40},{"species":"electivire","min":35,"max":45},{"species":"electrode","min":30,"max":40},{"species":"elekid","min":5,"max":15},{"species":"farfetchd","min":5,"max":15},{"species":"gligar","min":5,"max":15},{"species":"gliscor","min":20,"max":30},{"species":"golem","min":35,"max":45},{"species":"gyarados","min":20,"max":30},{"species":"honchkrow","min":20,"max":30},{"species":"iron-hands","min":5,"max":15},{"species":"iron-jugulis","min":5,"max":15},{"species":"iron-thorns","min":5,"max":15},{"species":"jolteon","min":20,"max":30},{"species":"jumpluff","min":27,"max":37},{"species":"luxray","min":30,"max":40},{"species":"magneton","min":30,"max":40},{"species":"magnezone","min":35,"max":45},{"species":"mandibuzz","min":54,"max":64},{"species":"manectric","min":26,"max":36},{"species":"mantine","min":20,"max":30},{"species":"mantyke","min":5,"max":15},{"species":"minior","min":5,"max":15},{"species":"mothim","min":20,"max":30},{"species":"murkrow","min":5,"max":15},{"species":"noivern","min":48,"max":58},{"species":"oricorio","min":5,"max":15},{"species":"pawmot","min":35,"max":45},{"species":"pelipper","min":25,"max":35},{"species":"pidgeot","min":36,"max":46},{"species":"pinsir","min":5,"max":15},{"species":"rotom","min":5,"max":15},{"species":"rowlet","min":5,"max":15},{"species":"salamence","min":50,"max":60},{"species":"sandy-shocks","min":5,"max":15},{"species":"scyther","min":5,"max":15},{"species":"sigilyph","min":5,"max":15},{"species":"skarmory","min":5,"max":15},{"species":"staraptor","min":34,"max":44},{"species":"swanna","min":35,"max":45},{"species":"swellow","min":22,"max":32},{"species":"swoobat","min":20,"max":30},{"species":"talonflame","min":35,"max":45},{"species":"togekiss","min":35,"max":45},{"species":"toucannon","min":28,"max":38},{"species":"toxtricity","min":30,"max":40},{"species":"unfezant","min":32,"max":42},{"species":"vespiquen","min":21,"max":31},{"species":"vikavolt","min":35,"max":45},{"species":"vivillon","min":12,"max":22},{"species":"xurkitree","min":5,"max":15},{"species":"yanmega","min":20,"max":30}],"very_rare":[{"species":"raging-bolt","min":5,"max":15}]},"berries":["pecha","lum","wepear","grepa","belue","wacan","coba","lansat"]}